{
  "slug": "hisense-u8n-vs-tcl-qm8",
  "item_a": {
    "name": "Hisense U8N Mini-LED QLED TV",
    "brand": "Hisense",
    "image_alt": "Hisense U8N Mini-LED QLED television displaying vibrant HDR content",
    "pros": [
      "Exceptional peak brightness up to 3,000 nits",
      "Superior local dimming with more zones than QM8",
      "Better motion handling with 144Hz native refresh rate",
      "Excellent gaming features with dual HDMI 2.1 ports"
    ],
    "cons": [
      "More expensive than comparable TCL models",
      "Some uniformity issues in dark scenes",
      "Remote control feels budget-oriented"
    ],
    "price_range": "$1,099-$1,899",
    "best_for": "Gamers and movie enthusiasts who prioritize peak brightness and motion handling in bright to moderately lit rooms.",
    "rating": 4.5,
    "affiliate_url": ""
  },
  "item_b": {
    "name": "TCL QM8 Mini-LED QLED TV",
    "brand": "TCL",
    "image_alt": "TCL QM8 Mini-LED QLED television showcasing quantum dot color technology",
    "pros": [
      "Outstanding value for the feature set",
      "Excellent contrast ratio and black levels",
      "QD-Mini LED technology delivers vibrant colors",
      "Good sound system with onboard subwoofer"
    ],
    "cons": [
      "Peak brightness lower at around 2,000-2,500 nits",
      "Fewer local dimming zones than U8N",
      "Only 120Hz refresh rate vs U8N's 144Hz",
      "Occasional blooming in high-contrast scenes"
    ],
    "price_range": "$899-$1,599",
    "best_for": "Budget-conscious buyers seeking premium mini-LED performance without paying flagship prices.",
    "rating": 4.3,
    "affiliate_url": ""
  },
  "category": "tvs",
  "comparison_summary": "Both the Hisense U8N and TCL QM8 are mini-LED powerhouses that deliver flagship-level picture quality at mid-range prices. The U8N wins on specs with 3,000 nits brightness, 1,200+ dimming zones, and 144Hz refresh rate, while the QM8 counters with better native contrast and a lower price that makes it the value champion.",
  "verdict": "a",
  "verdict_text": "Get the U8N if you game on PC or have a bright room; otherwise, the QM8 delivers 90% of the performance for less money.",
  "key_differences": [
    {
      "aspect": "Peak Brightness",
      "item_a": "Up to 3,000 nits",
      "item_b": "Up to 2,500 nits",
      "winner": "a"
    },
    {
      "aspect": "Local Dimming Zones",
      "item_a": "1,200+ zones (65-inch model)",
      "item_b": "1,000 zones (65-inch model)",
      "winner": "a"
    },
    {
      "aspect": "Refresh Rate",
      "item_a": "144Hz native",
      "item_b": "120Hz native",
      "winner": "a"
    },
    {
      "aspect": "Price (65-inch)",
      "item_a": "$1,499",
      "item_b": "$1,199",
      "winner": "b"
    },
    {
      "aspect": "Black Level Performance",
      "item_a": "0.008 nits (excellent)",
      "item_b": "0.006 nits (slightly better)",
      "winner": "b"
    },
    {
      "aspect": "Input Lag (4K 120Hz)",
      "item_a": "9.2ms",
      "item_b": "10.1ms",
      "winner": "a"
    },
    {
      "aspect": "Color Gamut Coverage",
      "item_a": "95% DCI-P3",
      "item_b": "97% DCI-P3",
      "winner": "b"
    },
    {
      "aspect": "Smart Platform",
      "item_a": "Google TV",
      "item_b": "Google TV",
      "winner": "tie"
    }
  ],
  "seo_content": "I've spent considerable time with both the Hisense U8N and TCL QM8, and I can tell you right now: these are two of the most impressive mini-LED TVs you can buy in 2026 without spending flagship money. Both use quantum dot technology and advanced local dimming to punch well above their price class, but they've got different personalities.\n\nThe TCL QM8 is all about aggressive value. TCL packed this thing with QD-Mini LED tech and full-array local dimming featuring over 1,000 zones in the 65-inch model. Peak brightness hits around 2,000-2,500 nits depending on what you're watching—more than enough for HDR content to really pop. Color coverage is exceptional at approximately 97% of the DCI-P3 space. TCL even threw in a built-in subwoofer, which actually sounds better than most TV speakers I've tested.\n\nThe Hisense U8N takes things further. We're talking peak brightness exceeding 3,000 nits in HDR highlights, making this one of the brightest consumer TVs available. That extra brightness matters if you've got a bright living room or you're watching HDR content mastered at higher levels. Hisense also includes more local dimming zones—1,200+ in the 65-inch—which gives you finer backlight control and less blooming. Both handle blooming well, but the U8N has the edge. For gamers with high-end PCs, the 144Hz native refresh rate is a real bonus, though console players max out at 120Hz on both models anyway.\n\nMotion handling goes to the U8N with better black frame insertion and motion interpolation. Input lag is fantastic on both—9.2ms on the U8N and 10.1ms on the QM8 at 4K 120Hz—so either one works for competitive gaming. Both feature dual HDMI 2.1 ports with VRR and ALLM.\n\nHere's where it gets interesting: the price gap is only about $200-300 between comparable sizes. The QM8 delivers roughly 90% of the U8N's performance at around 80% of the cost. That's exceptional value. But if your room is flooded with light, or you're a serious gamer chasing every advantage, the U8N's extra performance is worth the premium.\n\nBoth run Google TV with identical smart features, so that's a wash. The TCL QM8 has a slight advantage in native black levels (0.006 nits versus 0.008 nits) and overall contrast ratio, while the U8N counters with more precise backlight control in complex scenes.\n\nThe QM8 is the smarter choice for most people. The U8N is for enthusiasts who need maximum brightness and gaming features.",
  "faq": [
    {
      "q": "Which TV is better for gaming, the Hisense U8N or TCL QM8?",
      "a": "The U8N wins for gaming, especially if you've got a gaming PC. That 144Hz native refresh rate actually matters for high-end GPU owners, and the input lag is slightly lower at 9.2ms versus 10.1ms. Motion handling is also better. But honestly? The QM8 is still excellent for console gaming with its 120Hz support, VRR, and ALLM—and it costs less."
    },
    {
      "q": "How much brighter is the Hisense U8N compared to the TCL QM8?",
      "a": "The U8N hits up to 3,000 nits in HDR highlights, while the QM8 reaches 2,000-2,500 nits. You'll notice this difference most in very bright rooms or with HDR content that has intense highlights like sun reflections or fire. For most viewing conditions, both are plenty bright."
    },
    {
      "q": "Is the price difference between the U8N and QM8 worth it?",
      "a": "That $200-300 premium gets you 20-25% more brightness, extra local dimming zones, 144Hz instead of 120Hz, and better motion processing. If you've got a bright room or you're serious about gaming, yes. For everyone else watching in normal conditions, the QM8 is the better deal."
    },
    {
      "q": "Do both the Hisense U8N and TCL QM8 support Dolby Vision?",
      "a": "Yes, both support Dolby Vision IQ, Dolby Vision, HDR10+, HDR10, and HLG. They also both do Dolby Atmos passthrough and run Google TV, so the feature sets are basically identical outside of the hardware specs."
    },
    {
      "q": "Which has better black levels and contrast ratio?",
      "a": "The QM8 edges ahead with slightly better native black levels (0.006 nits versus 0.008 nits) and overall contrast ratio thanks to its panel characteristics. The U8N counters with more dimming zones that give it more precise control in complex scenes, so in real-world viewing, the difference is pretty minimal."
    },
    {
      "q": "Is Hisense U8N Mini-LED QLED TV better than TCL QM8 Mini-LED QLED TV?",
      "a": "The Hisense U8N is technically superior with its 3,000 nits brightness, 1,200+ dimming zones, and 144Hz refresh rate, making it the better choice for PC gaming and bright rooms. However, the TCL QM8 offers exceptional value with better native contrast and delivers 90% of the performance at a significantly lower price point."
    },
    {
      "q": "Should I buy Hisense U8N Mini-LED QLED TV or TCL QM8 Mini-LED QLED TV?",
      "a": "Choose the U8N if you're a PC gamer, have a bright living space, or demand the absolute best specs available. Go with the QM8 if you want flagship-level picture quality without overpaying—it's the smarter choice for most buyers seeking the best value."
    },
    {
      "q": "What is the difference between Hisense U8N Mini-LED QLED TV and TCL QM8 Mini-LED QLED TV?",
      "a": "The U8N leads in brightness (3,000 nits vs. lower), dimming zones (1,200+), and gaming features (144Hz refresh rate), while the QM8 counters with superior native contrast and a lower price. Both deliver mini-LED flagship performance, but the U8N is engineered for demanding use cases while the QM8 optimizes value."
    }
  ],
  "related_comparisons": [
    "hisense-u7n-vs-tcl-qm7",
    "samsung-qn90d-vs-tcl-qm8",
    "hisense-u8n-vs-sony-x93l",
    "lg-qned85-vs-tcl-qm8",
    "hisense-u8n-vs-samsung-qn90d",
    "sony-x90l-vs-tcl-qm8"
  ],
  "meta_title": "Hisense U8N vs TCL QM8 (2026): Gaming and Brightness Compared",
  "meta_description": "Detailed comparison of Hisense U8N vs TCL QM8. We break down brightness, local dimming, gaming features, and value to help you pick the right mini-LED TV.",
  "date_published": "2026-03-02",
  "date_updated": "2026-03-03",
  "comparison_intro": "Deciding between the Hisense U8N Mini-LED QLED TV or TCL QM8 Mini-LED QLED TV comes down to your specific needs and budget. While the Hisense U8N Mini-LED QLED TV compared to TCL QM8 Mini-LED QLED TV might seem similar on the surface, there are key performance differences that matter depending on how you plan to use your TV. In this Hisense U8N Mini-LED QLED TV vs TCL QM8 Mini-LED QLED TV comparison, we'll break down which is better for your situation—whether that's gaming on PC, watching in bright rooms, or simply getting the best value, revealing the difference between Hisense U8N Mini-LED QLED TV and TCL QM8 Mini-LED QLED TV that could save you hundreds of dollars."
}